setup.py
scripts/rosrelease-legacy
src/rosrelease/BeautifulSoup.py
src/rosrelease/__init__.py
src/rosrelease/executor.py
src/rosrelease/jenkins_support.py
src/rosrelease/legacy_main.py
src/rosrelease/release_base.py
src/rosrelease/rosdep_support.py
src/rosrelease/rosdistro_support.py
src/rosrelease/rospkg_support.py
src/rosrelease/sourcedeb_support.py
src/rosrelease/tarballer.py
src/rosrelease/vcs_support.py
src/rosrelease.egg-info/PKG-INFO
src/rosrelease.egg-info/SOURCES.txt
src/rosrelease.egg-info/dependency_links.txt
src/rosrelease.egg-info/requires.txt
src/rosrelease.egg-info/top_level.txt
test/test_jenkins_support.py
test/test_legacy_main.py
test/test_rosdep_support.py
test/test_rosdistro_support.py
test/test_rospkg_support.py
test/test_sourcedeb_support.py
test/test_vcs_support.py