Metadata-Version: 1.1
Name: rosrelease
Version: 0.2.11
Summary: ROS stack release support
Home-page: http://www.ros.org/wiki/rosrelease
Author: Ken Conley
Author-email: kwc@willowgarage.com
License: BSD
Download-URL: http://pr.willowgarage.com/downloads/rosrelease/
Keywords: ROS
Platform: UNKNOWN
Classifier: Programming Language :: Python
Classifier: License :: OSI Approved :: BSD License
